recurvedata/__init__.py
recurvedata/__version__.py
recurvedata/config.py
recurvedata/consts.py
recurvedata/error_codes.py
recurvedata/exceptions.py
recurvedata/provider_manager.py
recurvedata/schema.py
recurvedata/client/__init__.py
recurvedata/client/client.py
recurvedata/client/server_client.py
recurvedata/connectors/__init__.py
recurvedata/connectors/_register.py
recurvedata/connectors/base.py
recurvedata/connectors/config_schema.py
recurvedata/connectors/const.py
recurvedata/connectors/datasource.py
recurvedata/connectors/dbapi.py
recurvedata/connectors/fs.py
recurvedata/connectors/ftp.py
recurvedata/connectors/object_store.py
recurvedata/connectors/pigeon.py
recurvedata/connectors/proxy.py
recurvedata/connectors/service.py
recurvedata/connectors/utils.py
recurvedata/connectors/connectors/__init__.py
recurvedata/connectors/connectors/aliyun_access_key.py
recurvedata/connectors/connectors/auth.py
recurvedata/connectors/connectors/azure_blob.py
recurvedata/connectors/connectors/azure_synapse.py
recurvedata/connectors/connectors/bigquery.py
recurvedata/connectors/connectors/clickhouse.py
recurvedata/connectors/connectors/dingtalk.py
recurvedata/connectors/connectors/doris.py
recurvedata/connectors/connectors/es.py
recurvedata/connectors/connectors/feishu.py
recurvedata/connectors/connectors/flink.py
recurvedata/connectors/connectors/ftp.py
recurvedata/connectors/connectors/generic.py
recurvedata/connectors/connectors/google_cloud_storage.py
recurvedata/connectors/connectors/google_service_account.py
recurvedata/connectors/connectors/guanyuan_bi.py
recurvedata/connectors/connectors/hive.py
recurvedata/connectors/connectors/impala.py
recurvedata/connectors/connectors/jenkins.py
recurvedata/connectors/connectors/mail.py
recurvedata/connectors/connectors/microsoft_fabric.py
recurvedata/connectors/connectors/mongo.py
recurvedata/connectors/connectors/mssql.py
recurvedata/connectors/connectors/mysql.py
recurvedata/connectors/connectors/n8n.py
recurvedata_lib-0.1.543.dist-info/METADATA
recurvedata_lib-0.1.543.dist-info/WHEEL
recurvedata_lib-0.1.543.dist-info/entry_points.txt
recurvedata_lib-0.1.543.dist-info/RECORD
